{"nodes":[{"label":"MyTeacherIsWeird","x":-403.7579650878906,"y":-770.5405883789062,"id":"44","attributes":{"Modularity Class":"10","Component ID":"6","Grad":"1"},"color":"rgb(192,192,192)","size":17.5},{"label":"KansasCaucus","x":742.7039794921875,"y":211.20339965820312,"id":"95","attributes":{"Modularity Class":"42","Component ID":"0","Grad":"2"},"color":"rgb(241,8,123)","size":17.5},{"label":"WIPrimary","x":480.583740234375,"y":498.39373779296875,"id":"121","attributes":{"Modularity Class":"41","Component ID":"0","Grad":"9"},"color":"rgb(192,192,192)","size":17.5},{"label":"DivoDeJuarez","x":883.395263671875,"y":-754.1470336914062,"id":"218","attributes":{"Modularity Class":"5","Component ID":"12","Grad":"2"},"color":"rgb(192,192,192)","size":17.5},{"label":"Prince","x":-609.219970703125,"y":173.6483154296875,"id":"170","attributes":{"Modularity Class":"15","Component ID":"19","Grad":"1"},"color":"rgb(192,192,192)","size":17.5},{"label":"NeverHillary","x":27.437692642211914,"y":997.3138427734375,"id":"133","attributes":{"Modularity Class":"0","Component ID":"0","Grad":"6"},"color":"rgb(192,192,192)","size":17.5},{"label":"MeetTheTrumps","x":27.317459106445312,"y":-67.34203338623047,"id":"129","attributes":{"Modularity Class":"42","Component ID":"0","Grad":"1"},"color":"rgb(241,8,123)","size":17.5},{"label":"ObamaCare","x":278.9075622558594,"y":1140.8621826171875,"id":"104","attributes":{"Modularity Class":"28","Component ID":"0","Grad":"1"},"color":"rgb(192,192,192)","size":17.5},{"label":"ImWithYou","x":199.14967346191406,"y":176.49508666992188,"id":"137","attributes":{"Modularity Class":"4","Component ID":"0","Grad":"10"},"color":"rgb(95,165,253)","size":17.5},{"label":"StoptheHate","x":281.2485046386719,"y":-631.3842163085938,"id":"160","attributes":{"Modularity Class":"35","Component ID":"31","Grad":"1"},"color":"rgb(192,192,192)","size":17.5},{"label":"Hillary2016","x":-262.67852783203125,"y":973.8508911132812,"id":"222","attributes":{"Modularity Class":"6","Component ID":"13","Grad":"2"},"color":"rgb(192,192,192)","size":17.5},{"label":"CA4Trump","x":-876.4056396484375,"y":-242.5671844482422,"id":"143","attributes":{"Modularity Class":"3","Component ID":"7","Grad":"2"},"color":"rgb(192,192,192)","size":17.5},{"label":"SuperTuesday","x":673.5097045898438,"y":95.06874084472656,"id":"16","attributes":{"Modularity Class":"42","Component ID":"0","Grad":"4"},"color":"rgb(241,8,123)","size":17.5},{"label":"LeadRight2016","x":-181.55715942382812,"y":80.33091735839844,"id":"7","attributes":{"Modularity Class":"4","Component ID":"0","Grad":"1"},"color":"rgb(95,165,253)","size":17.5},{"label":"SCOTUS","x":-36.50706100463867,"y":1162.0782470703125,"id":"229","attributes":{"Modularity Class":"0","Component ID":"0","Grad":"2"},"color":"rgb(192,192,192)","size":17.5},{"label":"EndCommonCore","x":-19.94295883178711,"y":-201.5867156982422,"id":"28","attributes":{"Modularity Class":"42","Component ID":"0","Grad":"1"},"color":"rgb(241,8,123)","size":17.5},{"label":"GOPDebate","x":857.8098754882812,"y":588.0799560546875,"id":"189","attributes":{"Modularity Class":"41","Component ID":"0","Grad":"5"},"color":"rgb(192,192,192)","size":17.5},{"label":"EndGunViolence","x":-400.57818603515625,"y":-1093.9996337890625,"id":"83","attributes":{"Modularity Class":"43","Component ID":"5","Grad":"2"},"color":"rgb(192,192,192)","size":17.5},{"label":"NebraskaPrimary","x":449.34088134765625,"y":785.6987915039062,"id":"178","attributes":{"Modularity Class":"42","Component ID":"0","Grad":"2"},"color":"rgb(241,8,123)","size":17.5},{"label":"makeamericagreatagain","x":419.06121826171875,"y":-1093.84521484375,"id":"190","attributes":{"Modularity Class":"39","Component ID":"29","Grad":"3"},"color":"rgb(192,192,192)","size":17.5},{"label":"StopCommonCore","x":439.4908142089844,"y":-208.41102600097656,"id":"142","attributes":{"Modularity Class":"42","Component ID":"0","Grad":"1"},"color":"rgb(241,8,123)","size":17.5},{"label":"2016","x":-564.4235229492188,"y":-487.451904296875,"id":"181","attributes":{"Modularity Class":"37","Component ID":"32","Grad":"1"},"color":"rgb(192,192,192)","size":17.5},{"label":"enough","x":17.597484588623047,"y":-1044.0008544921875,"id":"48","attributes":{"Modularity Class":"38","Component ID":"17","Grad":"1"},"color":"rgb(192,192,192)","size":17.5},{"label":"MAKEAMERICAGREATAGAIN","x":436.17437744140625,"y":1082.5552978515625,"id":"171","attributes":{"Modularity Class":"28","Component ID":"0","Grad":"2"},"color":"rgb(192,192,192)","size":17.5},{"label":"MDPrimary","x":993.8355712890625,"y":-626.142333984375,"id":"206","attributes":{"Modularity Class":"40","Component ID":"0","Grad":"4"},"color":"rgb(192,192,192)","size":17.5},{"label":"Racine","x":598.5082397460938,"y":595.9653930664062,"id":"223","attributes":{"Modularity Class":"41","Component ID":"0","Grad":"5"},"color":"rgb(192,192,192)","size":17.5},{"label":"CBNNews","x":-474.56414794921875,"y":-609.1858520507812,"id":"167","attributes":{"Modularity Class":"37","Component ID":"32","Grad":"1"},"color":"rgb(192,192,192)","size":17.5},{"label":"holdthefloor","x":-899.4788208007812,"y":-741.780029296875,"id":"68","attributes":{"Modularity Class":"43","Component ID":"5","Grad":"2"},"color":"rgb(192,192,192)","size":17.5},{"label":"CrookedHillary","x":-83.59246826171875,"y":226.64434814453125,"id":"8","attributes":{"Modularity Class":"4","Component ID":"0","Grad":"3"},"color":"rgb(95,165,253)","size":17.5},{"label":"TrumpWon","x":-255.9880828857422,"y":820.9348754882812,"id":"59","attributes":{"Modularity Class":"4","Component ID":"0","Grad":"2"},"color":"rgb(95,165,253)","size":17.5},{"label":"AZPrimary","x":877.7509765625,"y":130.9462432861328,"id":"14","attributes":{"Modularity Class":"33","Component ID":"0","Grad":"7"},"color":"rgb(192,192,192)","size":17.5},{"label":"WashingtonDC","x":-759.6768188476562,"y":165.90162658691406,"id":"82","attributes":{"Modularity Class":"21","Component ID":"22","Grad":"1"},"color":"rgb(192,192,192)","size":17.5},{"label":"NHPolitics","x":739.5823364257812,"y":543.59521484375,"id":"66","attributes":{"Modularity Class":"32","Component ID":"0","Grad":"2"},"color":"rgb(192,192,192)","size":17.5},{"label":"SuperBowlSunday","x":815.2477416992188,"y":817.7833862304688,"id":"188","attributes":{"Modularity Class":"41","Component ID":"0","Grad":"2"},"color":"rgb(192,192,192)","size":17.5},{"label":"Rio2016","x":-745.76953125,"y":-511.8875427246094,"id":"70","attributes":{"Modularity Class":"18","Component ID":"8","Grad":"2"},"color":"rgb(192,192,192)","size":17.5},{"label":"SuperSaturday","x":510.69964599609375,"y":356.4530944824219,"id":"39","attributes":{"Modularity Class":"42","Component ID":"0","Grad":"1"},"color":"rgb(241,8,123)","size":17.5},{"label":"Utah4Trump","x":-334.7155456542969,"y":1103.68408203125,"id":"116","attributes":{"Modularity Class":"34","Component ID":"30","Grad":"4"},"color":"rgb(192,192,192)","size":17.5},{"label":"Clinton","x":-998.498046875,"y":-22.462297439575195,"id":"118","attributes":{"Modularity Class":"17","Component ID":"1","Grad":"1"},"color":"rgb(192,192,192)","size":17.5},{"label":"Mormon","x":-469.73687744140625,"y":1072.8140869140625,"id":"117","attributes":{"Modularity Class":"34","Component ID":"30","Grad":"4"},"color":"rgb(192,192,192)","size":17.5},{"label":"MAGA","x":-65.52181243896484,"y":469.3544921875,"id":"212","attributes":{"Modularity Class":"4","Component ID":"0","Grad":"16"},"color":"rgb(95,165,253)","size":17.5},{"label":"VoteTrumpNY","x":608.4736328125,"y":-193.4790802001953,"id":"20","attributes":{"Modularity Class":"41","Component ID":"0","Grad":"5"},"color":"rgb(192,192,192)","size":17.5},{"label":"Orlando","x":207.7514190673828,"y":-755.634765625,"id":"156","attributes":{"Modularity Class":"35","Component ID":"31","Grad":"1"},"color":"rgb(192,192,192)","size":17.5},{"label":"MaitnerStrong","x":61.045284271240234,"y":-903.0553588867188,"id":"155","attributes":{"Modularity Class":"24","Component ID":"23","Grad":"1"},"color":"rgb(192,192,192)","size":17.5},{"label":"MattSchlapp","x":724.4105834960938,"y":-706.2319946289062,"id":"64","attributes":{"Modularity Class":"16","Component ID":"0","Grad":"2"},"color":"rgb(192,192,192)","size":17.5},{"label":"GOPConvention","x":-3.73699688911438,"y":710.5000610351562,"id":"183","attributes":{"Modularity Class":"4","Component ID":"0","Grad":"3"},"color":"rgb(95,165,253)","size":17.5},{"label":"Trump","x":-1016.6557006835938,"y":-170.19277954101562,"id":"215","attributes":{"Modularity Class":"17","Component ID":"1","Grad":"5"},"color":"rgb(192,192,192)","size":17.5},{"label":"Colbert","x":-696.95703125,"y":546.9960327148438,"id":"106","attributes":{"Modularity Class":"29","Component ID":"27","Grad":"1"},"color":"rgb(192,192,192)","size":17.5},{"label":"MakeAmericaGreatAgain","x":543.7327880859375,"y":111.46107482910156,"id":"210","attributes":{"Modularity Class":"42","Component ID":"0","Grad":"37"},"color":"rgb(241,8,123)","size":17.5},{"label":"NewHampshire","x":1079.5882568359375,"y":457.8340148925781,"id":"139","attributes":{"Modularity Class":"32","Component ID":"0","Grad":"2"},"color":"rgb(192,192,192)","size":17.5},{"label":"VoteTrumpWI","x":597.6859741210938,"y":868.8594360351562,"id":"25","attributes":{"Modularity Class":"41","Component ID":"0","Grad":"1"},"color":"rgb(192,192,192)","size":17.5},{"label":"Pulse","x":-455.0836181640625,"y":-197.87619018554688,"id":"108","attributes":{"Modularity Class":"30","Component ID":"24","Grad":"1"},"color":"rgb(192,192,192)","size":17.5},{"label":"Polls","x":-524.9400024414062,"y":38.158626556396484,"id":"226","attributes":{"Modularity Class":"4","Component ID":"0","Grad":"2"},"color":"rgb(95,165,253)","size":17.5},{"label":"LoneStarState","x":893.5047607421875,"y":-93.92970275878906,"id":"100","attributes":{"Modularity Class":"42","Component ID":"0","Grad":"2"},"color":"rgb(241,8,123)","size":17.5},{"label":"ISIS","x":-519.954833984375,"y":297.0367431640625,"id":"126","attributes":{"Modularity Class":"4","Component ID":"0","Grad":"1"},"color":"rgb(95,165,253)","size":17.5},{"label":"AsLongAsItTakes","x":-526.8317260742188,"y":-884.9339599609375,"id":"10","attributes":{"Modularity Class":"43","Component ID":"5","Grad":"4"},"color":"rgb(192,192,192)","size":17.5},{"label":"BuildTheWall","x":314.3794250488281,"y":997.2440795898438,"id":"86","attributes":{"Modularity Class":"28","Component ID":"0","Grad":"1"},"color":"rgb(192,192,192)","size":17.5},{"label":"Fox","x":-1058.1041259765625,"y":104.11256408691406,"id":"154","attributes":{"Modularity Class":"1","Component ID":"3","Grad":"2"},"color":"rgb(192,192,192)","size":17.5},{"label":"IACaucus","x":630.6951293945312,"y":278.1650695800781,"id":"97","attributes":{"Modularity Class":"42","Component ID":"0","Grad":"7"},"color":"rgb(241,8,123)","size":17.5},{"label":"TeamTrump","x":47.875606536865234,"y":-765.58935546875,"id":"93","attributes":{"Modularity Class":"24","Component ID":"23","Grad":"1"},"color":"rgb(192,192,192)","size":17.5},{"label":"JimmyFallon","x":-462.39697265625,"y":685.612060546875,"id":"144","attributes":{"Modularity Class":"4","Component ID":"0","Grad":"3"},"color":"rgb(95,165,253)","size":17.5},{"label":"DisarmHate","x":-243.26849365234375,"y":-1148.6026611328125,"id":"131","attributes":{"Modularity Class":"43","Component ID":"5","Grad":"2"},"color":"rgb(192,192,192)","size":17.5},{"label":"CitizensUnited","x":-227.46075439453125,"y":-880.7643432617188,"id":"227","attributes":{"Modularity Class":"11","Component ID":"16","Grad":"1"},"color":"rgb(192,192,192)","size":17.5},{"label":"FallonTonight","x":-333.90435791015625,"y":-622.2676391601562,"id":"11","attributes":{"Modularity Class":"10","Component ID":"6","Grad":"1"},"color":"rgb(192,192,192)","size":17.5},{"label":"CAPrimary","x":277.1009521484375,"y":-233.9685821533203,"id":"158","attributes":{"Modularity Class":"42","Component ID":"0","Grad":"1"},"color":"rgb(241,8,123)","size":17.5},{"label":"jenniferrubin","x":560.9981689453125,"y":-728.0186157226562,"id":"161","attributes":{"Modularity Class":"16","Component ID":"0","Grad":"2"},"color":"rgb(192,192,192)","size":17.5},{"label":"OpeningCeremony","x":-953.7408447265625,"y":-482.1719665527344,"id":"228","attributes":{"Modularity Class":"18","Component ID":"8","Grad":"2"},"color":"rgb(192,192,192)","size":17.5},{"label":"gunviolence","x":-664.2815551757812,"y":-964.14990234375,"id":"50","attributes":{"Modularity Class":"43","Component ID":"5","Grad":"4"},"color":"rgb(192,192,192)","size":17.5},{"label":"BlacksForTrump","x":-392.9335021972656,"y":802.7652587890625,"id":"103","attributes":{"Modularity Class":"6","Component ID":"13","Grad":"2"},"color":"rgb(192,192,192)","size":17.5},{"label":"DemsInPhilly","x":-133.3746337890625,"y":-1041.510986328125,"id":"185","attributes":{"Modularity Class":"38","Component ID":"17","Grad":"4"},"color":"rgb(192,192,192)","size":17.5},{"label":"PAPrimary","x":963.9481811523438,"y":-353.8973693847656,"id":"199","attributes":{"Modularity Class":"40","Component ID":"0","Grad":"5"},"color":"rgb(192,192,192)","size":17.5},{"label":"CaucusForTrump","x":632.2642822265625,"y":447.1229553222656,"id":"186","attributes":{"Modularity Class":"42","Component ID":"0","Grad":"1"},"color":"rgb(241,8,123)","size":17.5},{"label":"BikersForTrump","x":179.8014678955078,"y":-507.5704345703125,"id":"67","attributes":{"Modularity Class":"22","Component ID":"0","Grad":"1"},"color":"rgb(192,192,192)","size":17.5},{"label":"LawandOrder","x":-230.18850708007812,"y":221.068115234375,"id":"224","attributes":{"Modularity Class":"4","Component ID":"0","Grad":"1"},"color":"rgb(95,165,253)","size":17.5},{"label":"ClintonKaine","x":200.17001342773438,"y":-903.135009765625,"id":"56","attributes":{"Modularity Class":"38","Component ID":"17","Grad":"1"},"color":"rgb(192,192,192)","size":17.5},{"label":"HillaryOnGMA","x":-611.1474609375,"y":423.7352294921875,"id":"172","attributes":{"Modularity Class":"4","Component ID":"0","Grad":"1"},"color":"rgb(95,165,253)","size":17.5},{"label":"Debates2016","x":-323.9151916503906,"y":91.71134185791016,"id":"127","attributes":{"Modularity Class":"4","Component ID":"0","Grad":"8"},"color":"rgb(95,165,253)","size":17.5},{"label":"GOPinCLE","x":-139.60650634765625,"y":741.0626220703125,"id":"63","attributes":{"Modularity Class":"4","Component ID":"0","Grad":"2"},"color":"rgb(95,165,253)","size":17.5},{"label":"VoterRegistrationDay","x":341.7417297363281,"y":-103.15056610107422,"id":"112","attributes":{"Modularity Class":"42","Component ID":"0","Grad":"1"},"color":"rgb(241,8,123)","size":17.5},{"label":"RNC","x":261.2314453125,"y":29.899173736572266,"id":"168","attributes":{"Modularity Class":"42","Component ID":"0","Grad":"1"},"color":"rgb(241,8,123)","size":17.5},{"label":"Mexico","x":-1154.231689453125,"y":-135.86788940429688,"id":"3","attributes":{"Modularity Class":"17","Component ID":"1","Grad":"4"},"color":"rgb(192,192,192)","size":17.5},{"label":"Jonas","x":840.7245483398438,"y":-611.868408203125,"id":"150","attributes":{"Modularity Class":"36","Component ID":"0","Grad":"2"},"color":"rgb(192,192,192)","size":17.5},{"label":"RNCinCLE","x":46.92623519897461,"y":581.7077026367188,"id":"141","attributes":{"Modularity Class":"4","Component ID":"0","Grad":"5"},"color":"rgb(95,165,253)","size":17.5},{"label":"TrumpCountry","x":-206.4845428466797,"y":1146.2188720703125,"id":"145","attributes":{"Modularity Class":"34","Component ID":"30","Grad":"4"},"color":"rgb(192,192,192)","size":17.5},{"label":"Statehood","x":-826.611083984375,"y":29.168676376342773,"id":"195","attributes":{"Modularity Class":"21","Component ID":"22","Grad":"1"},"color":"rgb(192,192,192)","size":17.5},{"label":"VoteTrumpNH","x":1125.19091796875,"y":297.614990234375,"id":"0","attributes":{"Modularity Class":"32","Component ID":"0","Grad":"4"},"color":"rgb(192,192,192)","size":17.5},{"label":"Filibuster","x":-707.8965454101562,"y":934.5138549804688,"id":"58","attributes":{"Modularity Class":"13","Component ID":"10","Grad":"2"},"color":"rgb(192,192,192)","size":17.5},{"label":"SecondAmendment","x":-110.0921630859375,"y":1042.6243896484375,"id":"220","attributes":{"Modularity Class":"0","Component ID":"0","Grad":"1"},"color":"rgb(192,192,192)","size":17.5},{"label":"MothersoftheMovement","x":340.4493408203125,"y":-978.2434692382812,"id":"138","attributes":{"Modularity Class":"14","Component ID":"18","Grad":"2"},"color":"rgb(192,192,192)","size":17.5},{"label":"CTPrimary","x":939.2583618164062,"y":-498.8182678222656,"id":"32","attributes":{"Modularity Class":"40","Component ID":"0","Grad":"4"},"color":"rgb(192,192,192)","size":17.5},{"label":"debatenight","x":-269.24578857421875,"y":-53.766151428222656,"id":"164","attributes":{"Modularity Class":"4","Component ID":"0","Grad":"2"},"color":"rgb(95,165,253)","size":17.5},{"label":"VoteTrumpSC","x":355.21429443359375,"y":140.41180419921875,"id":"15","attributes":{"Modularity Class":"42","Component ID":"0","Grad":"3"},"color":"rgb(241,8,123)","size":17.5},{"label":"CommonLaw","x":-1060.678466796875,"y":468.8832092285156,"id":"29","attributes":{"Modularity Class":"9","Component ID":"9","Grad":"3"},"color":"rgb(192,192,192)","size":17.5},{"label":"TRUMP2016","x":-310.6886291503906,"y":396.7304992675781,"id":"136","attributes":{"Modularity Class":"4","Component ID":"0","Grad":"1"},"color":"rgb(95,165,253)","size":17.5},{"label":"AZ","x":-772.8709716796875,"y":677.0501708984375,"id":"187","attributes":{"Modularity Class":"8","Component ID":"15","Grad":"1"},"color":"rgb(192,192,192)","size":17.5},{"label":"POTUS","x":755.2125854492188,"y":-137.00697326660156,"id":"200","attributes":{"Modularity Class":"41","Component ID":"0","Grad":"5"},"color":"rgb(192,192,192)","size":17.5},{"label":"MichaelMoore","x":579.6444091796875,"y":1014.3562622070312,"id":"73","attributes":{"Modularity Class":"19","Component ID":"0","Grad":"2"},"color":"rgb(192,192,192)","size":17.5},{"label":"NeverCruz","x":117.70641326904297,"y":-634.8224487304688,"id":"148","attributes":{"Modularity Class":"31","Component ID":"28","Grad":"1"},"color":"rgb(192,192,192)","size":17.5},{"label":"DNCinPHL","x":-915.8646850585938,"y":137.23304748535156,"id":"157","attributes":{"Modularity Class":"26","Component ID":"26","Grad":"1"},"color":"rgb(192,192,192)","size":17.5},{"label":"INPrimary","x":652.2982177734375,"y":-38.724430084228516,"id":"79","attributes":{"Modularity Class":"42","Component ID":"0","Grad":"3"},"color":"rgb(241,8,123)","size":17.5},{"label":"Utah","x":-406.9003601074219,"y":944.641357421875,"id":"211","attributes":{"Modularity Class":"34","Component ID":"30","Grad":"4"},"color":"rgb(192,192,192)","size":17.5},{"label":"JuanGabriel","x":649.99267578125,"y":-836.8012084960938,"id":"85","attributes":{"Modularity Class":"5","Component ID":"12","Grad":"2"},"color":"rgb(192,192,192)","size":17.5},{"label":"NewYork","x":816.051025390625,"y":-424.51458740234375,"id":"165","attributes":{"Modularity Class":"36","Component ID":"0","Grad":"2"},"color":"rgb(192,192,192)","size":17.5},{"label":"WCS16","x":-121.82425689697266,"y":-65.85003662109375,"id":"115","attributes":{"Modularity Class":"4","Component ID":"0","Grad":"1"},"color":"rgb(95,165,253)","size":17.5},{"label":"AmericaFirst","x":3.7644262313842773,"y":345.71807861328125,"id":"30","attributes":{"Modularity Class":"4","Component ID":"0","Grad":"13"},"color":"rgb(95,165,253)","size":17.5},{"label":"SCPrimary","x":427.47894287109375,"y":20.588642120361328,"id":"72","attributes":{"Modularity Class":"42","Component ID":"0","Grad":"3"},"color":"rgb(241,8,123)","size":17.5},{"label":"NYPrimary","x":521.2418823242188,"y":-78.40126037597656,"id":"19","attributes":{"Modularity Class":"42","Component ID":"0","Grad":"5"},"color":"rgb(241,8,123)","size":17.5},{"label":"NaturalBorn","x":-998.2769165039062,"y":585.2454223632812,"id":"21","attributes":{"Modularity Class":"9","Component ID":"9","Grad":"3"},"color":"rgb(192,192,192)","size":17.5},{"label":"GOP","x":718.9682006835938,"y":-538.42529296875,"id":"55","attributes":{"Modularity Class":"16","Component ID":"0","Grad":"3"},"color":"rgb(192,192,192)","size":17.5},{"label":"trump2016","x":534.8756713867188,"y":-321.521728515625,"id":"169","attributes":{"Modularity Class":"42","Component ID":"0","Grad":"3"},"color":"rgb(241,8,123)","size":17.5},{"label":"Carrier","x":-1128.918701171875,"y":-278.3520812988281,"id":"65","attributes":{"Modularity Class":"17","Component ID":"1","Grad":"4"},"color":"rgb(192,192,192)","size":17.5},{"label":"UT","x":-612.5057983398438,"y":681.0540771484375,"id":"38","attributes":{"Modularity Class":"8","Component ID":"15","Grad":"1"},"color":"rgb(192,192,192)","size":17.5},{"label":"TrumpNV","x":163.70986938476562,"y":321.619873046875,"id":"4","attributes":{"Modularity Class":"42","Component ID":"0","Grad":"1"},"color":"rgb(241,8,123)","size":17.5},{"label":"NewYorkValues","x":843.5285034179688,"y":-256.53759765625,"id":"149","attributes":{"Modularity Class":"36","Component ID":"0","Grad":"5"},"color":"rgb(192,192,192)","size":17.5},{"label":"ADA","x":-751.9275512695312,"y":-698.6073608398438,"id":"204","attributes":{"Modularity Class":"12","Component ID":"11","Grad":"2"},"color":"rgb(192,192,192)","size":17.5},{"label":"RTM2016","x":108.3045654296875,"y":51.95464324951172,"id":"99","attributes":{"Modularity Class":"42","Component ID":"0","Grad":"1"},"color":"rgb(241,8,123)","size":17.5},{"label":"FeelTheBern","x":173.5607452392578,"y":-1041.462890625,"id":"166","attributes":{"Modularity Class":"38","Component ID":"17","Grad":"1"},"color":"rgb(192,192,192)","size":17.5},{"label":"VoterFraud","x":-500.2740478515625,"y":-350.5487976074219,"id":"193","attributes":{"Modularity Class":"44","Component ID":"33","Grad":"1"},"color":"rgb(192,192,192)","size":17.5},{"label":"ImWithHer","x":100.03878784179688,"y":-1165.6181640625,"id":"221","attributes":{"Modularity Class":"38","Component ID":"17","Grad":"5"},"color":"rgb(192,192,192)","size":17.5},{"label":"Hannity","x":449.12322998046875,"y":923.316650390625,"id":"177","attributes":{"Modularity Class":"28","Component ID":"0","Grad":"3"},"color":"rgb(192,192,192)","size":17.5},{"label":"TPP","x":-172.05393981933594,"y":-206.51651000976562,"id":"47","attributes":{"Modularity Class":"4","Component ID":"0","Grad":"1"},"color":"rgb(95,165,253)","size":17.5},{"label":"ECONOMY","x":755.436767578125,"y":376.0421142578125,"id":"52","attributes":{"Modularity Class":"42","Component ID":"0","Grad":"2"},"color":"rgb(241,8,123)","size":17.5},{"label":"DEPrimary","x":1078.2266845703125,"y":-465.1901550292969,"id":"120","attributes":{"Modularity Class":"40","Component ID":"0","Grad":"4"},"color":"rgb(192,192,192)","size":17.5},{"label":"AmericanSamoa","x":1149.64697265625,"y":137.17425537109375,"id":"153","attributes":{"Modularity Class":"33","Component ID":"0","Grad":"5"},"color":"rgb(192,192,192)","size":17.5},{"label":"1","x":-127.3621597290039,"y":901.2258911132812,"id":"214","attributes":{"Modularity Class":"4","Component ID":"0","Grad":"1"},"color":"rgb(95,165,253)","size":17.5},{"label":"sitin","x":-527.1065063476562,"y":-1030.1741943359375,"id":"57","attributes":{"Modularity Class":"43","Component ID":"5","Grad":"6"},"color":"rgb(192,192,192)","size":17.5},{"label":"Mahalo","x":-739.4112548828125,"y":-258.4330749511719,"id":"140","attributes":{"Modularity Class":"2","Component ID":"4","Grad":"1"},"color":"rgb(192,192,192)","size":17.5},{"label":"NationalVoterRegistrationDay","x":-452.29779052734375,"y":155.37554931640625,"id":"209","attributes":{"Modularity Class":"4","Component ID":"0","Grad":"1"},"color":"rgb(95,165,253)","size":17.5},{"label":"NoMoreSilence","x":-662.2496337890625,"y":-816.8025512695312,"id":"174","attributes":{"Modularity Class":"43","Component ID":"5","Grad":"5"},"color":"rgb(192,192,192)","size":17.5},{"label":"USA","x":230.8914031982422,"y":-369.57672119140625,"id":"49","attributes":{"Modularity Class":"42","Component ID":"0","Grad":"1"},"color":"rgb(241,8,123)","size":17.5},{"label":"MichaelBrown","x":337.46563720703125,"y":-841.4141235351562,"id":"119","attributes":{"Modularity Class":"14","Component ID":"18","Grad":"2"},"color":"rgb(192,192,192)","size":17.5},{"label":"TedCruz","x":-1110.4578857421875,"y":342.23455810546875,"id":"41","attributes":{"Modularity Class":"9","Component ID":"9","Grad":"4"},"color":"rgb(192,192,192)","size":17.5},{"label":"WesternTuesday","x":330.7929382324219,"y":568.6864624023438,"id":"225","attributes":{"Modularity Class":"41","Component ID":"0","Grad":"2"},"color":"rgb(192,192,192)","size":17.5},{"label":"OrlandoUnited","x":-678.5323486328125,"y":802.4191284179688,"id":"33","attributes":{"Modularity Class":"13","Component ID":"10","Grad":"2"},"color":"rgb(192,192,192)","size":17.5},{"label":"TheDonald","x":-535.5138549804688,"y":552.9049682617188,"id":"124","attributes":{"Modularity Class":"4","Component ID":"0","Grad":"3"},"color":"rgb(95,165,253)","size":17.5},{"label":"AlwaysTrump","x":97.52050018310547,"y":457.5533142089844,"id":"75","attributes":{"Modularity Class":"41","Component ID":"0","Grad":"3"},"color":"rgb(192,192,192)","size":17.5},{"label":"TeamUSA","x":-858.4321899414062,"y":-594.5416259765625,"id":"13","attributes":{"Modularity Class":"18","Component ID":"8","Grad":"2"},"color":"rgb(192,192,192)","size":17.5},{"label":"HillaryClinton","x":-675.581298828125,"y":32.30300521850586,"id":"61","attributes":{"Modularity Class":"15","Component ID":"19","Grad":"1"},"color":"rgb(192,192,192)","size":17.5},{"label":"campaignfinance","x":-104.44080352783203,"y":-760.8547973632812,"id":"45","attributes":{"Modularity Class":"11","Component ID":"16","Grad":"1"},"color":"rgb(192,192,192)","size":17.5},{"label":"NevadaCaucus","x":-60.996463775634766,"y":-346.2906494140625,"id":"87","attributes":{"Modularity Class":"22","Component ID":"0","Grad":"1"},"color":"rgb(192,192,192)","size":17.5},{"label":"Wausau","x":598.5068359375,"y":733.1033935546875,"id":"207","attributes":{"Modularity Class":"41","Component ID":"0","Grad":"5"},"color":"rgb(192,192,192)","size":17.5},{"label":"Rubio","x":-262.3143615722656,"y":-485.71771240234375,"id":"194","attributes":{"Modularity Class":"45","Component ID":"34","Grad":"1"},"color":"rgb(192,192,192)","size":17.5},{"label":"NeverDems","x":-831.7883911132812,"y":-394.28076171875,"id":"12","attributes":{"Modularity Class":"3","Component ID":"7","Grad":"2"},"color":"rgb(192,192,192)","size":17.5},{"label":"UtahCaucus","x":993.4905395507812,"y":54.52164840698242,"id":"113","attributes":{"Modularity Class":"33","Component ID":"0","Grad":"7"},"color":"rgb(192,192,192)","size":17.5},{"label":"DemsinPhilly","x":-850.6054077148438,"y":283.0215148925781,"id":"98","attributes":{"Modularity Class":"26","Component ID":"26","Grad":"2"},"color":"rgb(192,192,192)","size":17.5},{"label":"TrumpTrain","x":367.1907043457031,"y":411.6142883300781,"id":"180","attributes":{"Modularity Class":"41","Component ID":"0","Grad":"15"},"color":"rgb(192,192,192)","size":17.5},{"label":"ORPrimary","x":1152.8431396484375,"y":-170.94723510742188,"id":"152","attributes":{"Modularity Class":"42","Component ID":"0","Grad":"1"},"color":"rgb(241,8,123)","size":17.5},{"label":"Ford","x":-1092.2034912109375,"y":-425.8661804199219,"id":"81","attributes":{"Modularity Class":"17","Component ID":"1","Grad":"4"},"color":"rgb(192,192,192)","size":17.5},{"label":"primary","x":185.45188903808594,"y":618.3984985351562,"id":"74","attributes":{"Modularity Class":"42","Component ID":"0","Grad":"2"},"color":"rgb(241,8,123)","size":17.5},{"label":"SB50","x":920.9497680664062,"y":720.0590209960938,"id":"134","attributes":{"Modularity Class":"41","Component ID":"0","Grad":"2"},"color":"rgb(192,192,192)","size":17.5},{"label":"FITN","x":883.0853881835938,"y":442.95355224609375,"id":"111","attributes":{"Modularity Class":"32","Component ID":"0","Grad":"9"},"color":"rgb(192,192,192)","size":17.5},{"label":"LaurenceTribe","x":-933.583251953125,"y":405.16046142578125,"id":"89","attributes":{"Modularity Class":"9","Component ID":"9","Grad":"1"},"color":"rgb(192,192,192)","size":17.5},{"label":"UtahPrimary","x":-573.8082885742188,"y":987.125,"id":"151","attributes":{"Modularity Class":"34","Component ID":"30","Grad":"4"},"color":"rgb(192,192,192)","size":17.5},{"label":"TheTonightShow","x":-381.678466796875,"y":561.405517578125,"id":"128","attributes":{"Modularity Class":"4","Component ID":"0","Grad":"3"},"color":"rgb(95,165,253)","size":17.5},{"label":"Politician","x":406.2716979980469,"y":-729.47216796875,"id":"5","attributes":{"Modularity Class":"23","Component ID":"2","Grad":"1"},"color":"rgb(192,192,192)","size":17.5},{"label":"WeWantTrump","x":647.6349487304688,"y":-975.97509765625,"id":"110","attributes":{"Modularity Class":"39","Component ID":"29","Grad":"3"},"color":"rgb(192,192,192)","size":17.5},{"label":"VotersSpeak","x":337.76263427734375,"y":-483.8005676269531,"id":"175","attributes":{"Modularity Class":"42","Component ID":"0","Grad":"1"},"color":"rgb(241,8,123)","size":17.5},{"label":"slipping","x":-413.38714599609375,"y":-46.78030014038086,"id":"205","attributes":{"Modularity Class":"4","Component ID":"0","Grad":"2"},"color":"rgb(95,165,253)","size":17.5},{"label":"Wisconsin","x":311.431640625,"y":283.7091979980469,"id":"201","attributes":{"Modularity Class":"41","Component ID":"0","Grad":"2"},"color":"rgb(192,192,192)","size":17.5},{"label":"ICYMI","x":643.3601684570312,"y":-414.2230224609375,"id":"90","attributes":{"Modularity Class":"41","Component ID":"0","Grad":"3"},"color":"rgb(192,192,192)","size":17.5},{"label":"BlackMenForBernie","x":-535.451416015625,"y":841.1783447265625,"id":"36","attributes":{"Modularity Class":"6","Component ID":"13","Grad":"2"},"color":"rgb(192,192,192)","size":17.5},{"label":"presidenttrump","x":302.16387939453125,"y":846.5333862304688,"id":"173","attributes":{"Modularity Class":"42","Component ID":"0","Grad":"2"},"color":"rgb(241,8,123)","size":17.5},{"label":"RIPrimary","x":1111.9390869140625,"y":-315.6153259277344,"id":"132","attributes":{"Modularity Class":"40","Component ID":"0","Grad":"5"},"color":"rgb(192,192,192)","size":17.5},{"label":"TrumpIsWithYou","x":234.54591369628906,"y":458.0180969238281,"id":"162","attributes":{"Modularity Class":"4","Component ID":"0","Grad":"2"},"color":"rgb(95,165,253)","size":17.5},{"label":"taxplan","x":-350.58056640625,"y":-332.63568115234375,"id":"102","attributes":{"Modularity Class":"27","Component ID":"21","Grad":"1"},"color":"rgb(192,192,192)","size":17.5},{"label":"Women4Ttump","x":-38.82160568237305,"y":76.8176498413086,"id":"202","attributes":{"Modularity Class":"42","Component ID":"0","Grad":"1"},"color":"rgb(241,8,123)","size":17.5},{"label":"LGBT","x":-573.7149658203125,"y":-98.88087463378906,"id":"94","attributes":{"Modularity Class":"30","Component ID":"24","Grad":"1"},"color":"rgb(192,192,192)","size":17.5},{"label":"StandTogether","x":-388.3679504394531,"y":-918.6619262695312,"id":"146","attributes":{"Modularity Class":"38","Component ID":"17","Grad":"1"},"color":"rgb(192,192,192)","size":17.5},{"label":"ElectionDay","x":106.43106842041016,"y":1160.0135498046875,"id":"147","attributes":{"Modularity Class":"0","Component ID":"0","Grad":"3"},"color":"rgb(192,192,192)","size":17.5},{"label":"UTCaucus","x":1013.6797485351562,"y":196.48410034179688,"id":"40","attributes":{"Modularity Class":"33","Component ID":"0","Grad":"7"},"color":"rgb(192,192,192)","size":17.5},{"label":"WattersWorld","x":184.56399536132812,"y":-88.95162200927734,"id":"69","attributes":{"Modularity Class":"42","Component ID":"0","Grad":"1"},"color":"rgb(241,8,123)","size":17.5},{"label":"TrumpMovement","x":-365.6079406738281,"y":269.1841735839844,"id":"53","attributes":{"Modularity Class":"4","Component ID":"0","Grad":"1"},"color":"rgb(95,165,253)","size":17.5},{"label":"WeAreBernie","x":277.0810546875,"y":-1132.6380615234375,"id":"213","attributes":{"Modularity Class":"39","Component ID":"29","Grad":"3"},"color":"rgb(192,192,192)","size":17.5},{"label":"imwithher","x":-639.5201416015625,"y":-613.6655883789062,"id":"34","attributes":{"Modularity Class":"12","Component ID":"11","Grad":"2"},"color":"rgb(192,192,192)","size":17.5},{"label":"CripTheVote","x":-548.1743774414062,"y":-730.8573608398438,"id":"51","attributes":{"Modularity Class":"12","Component ID":"11","Grad":"2"},"color":"rgb(192,192,192)","size":17.5},{"label":"GIBill","x":-261.01434326171875,"y":-750.0916137695312,"id":"96","attributes":{"Modularity Class":"25","Component ID":"25","Grad":"1"},"color":"rgb(192,192,192)","size":17.5},{"label":"DemConvention","x":-67.7001953125,"y":-1170.585205078125,"id":"135","attributes":{"Modularity Class":"38","Component ID":"17","Grad":"2"},"color":"rgb(192,192,192)","size":17.5},{"label":"ChangeAgents","x":489.332275390625,"y":-870.0736694335938,"id":"60","attributes":{"Modularity Class":"14","Component ID":"18","Grad":"2"},"color":"rgb(192,192,192)","size":17.5},{"label":"TrumpForPresident","x":302.3108825683594,"y":712.7747802734375,"id":"197","attributes":{"Modularity Class":"42","Component ID":"0","Grad":"2"},"color":"rgb(241,8,123)","size":17.5},{"label":"LSSC","x":-688.6957397460938,"y":303.1988220214844,"id":"130","attributes":{"Modularity Class":"29","Component ID":"27","Grad":"1"},"color":"rgb(192,192,192)","size":17.5},{"label":"NoBillNoBreak","x":-795.4480590820312,"y":-856.716064453125,"id":"216","attributes":{"Modularity Class":"43","Component ID":"5","Grad":"6"},"color":"rgb(192,192,192)","size":17.5},{"label":"NewDay","x":384.6479187011719,"y":-348.3442687988281,"id":"23","attributes":{"Modularity Class":"42","Component ID":"0","Grad":"1"},"color":"rgb(241,8,123)","size":17.5},{"label":"VoteTrump2016","x":142.4491729736328,"y":756.9657592773438,"id":"191","attributes":{"Modularity Class":"41","Component ID":"0","Grad":"1"},"color":"rgb(192,192,192)","size":17.5},{"label":"goodtrouble","x":-1006.3630981445312,"y":-611.6607666015625,"id":"182","attributes":{"Modularity Class":"43","Component ID":"5","Grad":"1"},"color":"rgb(192,192,192)","size":17.5},{"label":"DebateNight","x":-169.14227294921875,"y":359.62249755859375,"id":"42","attributes":{"Modularity Class":"4","Component ID":"0","Grad":"5"},"color":"rgb(95,165,253)","size":17.5},{"label":"Bush","x":-406.18890380859375,"y":-473.0081481933594,"id":"231","attributes":{"Modularity Class":"45","Component ID":"34","Grad":"1"},"color":"rgb(192,192,192)","size":17.5},{"label":"brexit","x":-284.78826904296875,"y":669.2561645507812,"id":"176","attributes":{"Modularity Class":"4","Component ID":"0","Grad":"1"},"color":"rgb(95,165,253)","size":17.5},{"label":"trump","x":518.9359741210938,"y":-1009.1821899414062,"id":"198","attributes":{"Modularity Class":"39","Component ID":"29","Grad":"3"},"color":"rgb(192,192,192)","size":17.5},{"label":"TrumpPence16","x":-237.4043426513672,"y":512.4910278320312,"id":"31","attributes":{"Modularity Class":"4","Component ID":"0","Grad":"7"},"color":"rgb(95,165,253)","size":17.5},{"label":"IowaCaucus","x":1168.290283203125,"y":-8.599710464477539,"id":"27","attributes":{"Modularity Class":"42","Component ID":"0","Grad":"1"},"color":"rgb(241,8,123)","size":17.5},{"label":"DefendtheSecond","x":167.98194885253906,"y":1039.225830078125,"id":"76","attributes":{"Modularity Class":"0","Component ID":"0","Grad":"3"},"color":"rgb(192,192,192)","size":17.5},{"label":"VoteTrumpNV","x":89.61638641357422,"y":-343.0129699707031,"id":"2","attributes":{"Modularity Class":"22","Component ID":"0","Grad":"3"},"color":"rgb(192,192,192)","size":17.5},{"label":"LyingTed","x":-29.145536422729492,"y":-625.322021484375,"id":"109","attributes":{"Modularity Class":"31","Component ID":"28","Grad":"1"},"color":"rgb(192,192,192)","size":17.5},{"label":"NeverForget","x":-112.56733703613281,"y":-486.3546447753906,"id":"125","attributes":{"Modularity Class":"20","Component ID":"20","Grad":"1"},"color":"rgb(192,192,192)","size":17.5},{"label":"Jobs","x":-1161.949462890625,"y":0.035283662378787994,"id":"105","attributes":{"Modularity Class":"17","Component ID":"1","Grad":"4"},"color":"rgb(192,192,192)","size":17.5},{"label":"FAIL","x":439.4221496582031,"y":-599.7275390625,"id":"91","attributes":{"Modularity Class":"23","Component ID":"2","Grad":"1"},"color":"rgb(192,192,192)","size":17.5},{"label":"Teachers4Trump","x":-982.0721435546875,"y":-332.3881530761719,"id":"84","attributes":{"Modularity Class":"3","Component ID":"7","Grad":"2"},"color":"rgb(192,192,192)","size":17.5},{"label":"VoteTrump","x":806.1558837890625,"y":24.49892807006836,"id":"208","attributes":{"Modularity Class":"42","Component ID":"0","Grad":"21"},"color":"rgb(241,8,123)","size":17.5},{"label":"RIP","x":786.91552734375,"y":-863.755615234375,"id":"35","attributes":{"Modularity Class":"5","Component ID":"12","Grad":"2"},"color":"rgb(192,192,192)","size":17.5},{"label":"ROGERAILES","x":720.6068115234375,"y":920.2987060546875,"id":"219","attributes":{"Modularity Class":"19","Component ID":"0","Grad":"2"},"color":"rgb(192,192,192)","size":17.5},{"label":"Enough","x":-829.5094604492188,"y":821.5714721679688,"id":"24","attributes":{"Modularity Class":"13","Component ID":"10","Grad":"2"},"color":"rgb(192,192,192)","size":17.5},{"label":"NATO","x":-281.5736389160156,"y":-1010.7388916015625,"id":"54","attributes":{"Modularity Class":"38","Component ID":"17","Grad":"2"},"color":"rgb(192,192,192)","size":17.5},{"label":"LaborDay","x":-128.92825317382812,"y":599.8401489257812,"id":"46","attributes":{"Modularity Class":"4","Component ID":"0","Grad":"1"},"color":"rgb(95,165,253)","size":17.5},{"label":"NASCAR","x":1037.4398193359375,"y":-70.39204406738281,"id":"107","attributes":{"Modularity Class":"42","Component ID":"0","Grad":"2"},"color":"rgb(241,8,123)","size":17.5},{"label":"MakeYoutubeGreatAgain","x":127.21358489990234,"y":-211.01666259765625,"id":"18","attributes":{"Modularity Class":"42","Component ID":"0","Grad":"1"},"color":"rgb(241,8,123)","size":17.5},{"label":"TrumpWaikiki","x":-666.963134765625,"y":-386.6828308105469,"id":"9","attributes":{"Modularity Class":"2","Component ID":"4","Grad":"1"},"color":"rgb(192,192,192)","size":17.5},{"label":"TBT","x":-450.6698303222656,"y":425.6889953613281,"id":"101","attributes":{"Modularity Class":"4","Component ID":"0","Grad":"2"},"color":"rgb(95,165,253)","size":17.5},{"label":"KenLangone","x":-1003.4334716796875,"y":256.2933349609375,"id":"159","attributes":{"Modularity Class":"1","Component ID":"3","Grad":"2"},"color":"rgb(192,192,192)","size":17.5},{"label":"LoveTrumpsHate","x":-82.3885726928711,"y":-904.6232299804688,"id":"196","attributes":{"Modularity Class":"38","Component ID":"17","Grad":"1"},"color":"rgb(192,192,192)","size":17.5},{"label":"NeilCavuto","x":-1160.219482421875,"y":187.1840057373047,"id":"6","attributes":{"Modularity Class":"1","Component ID":"3","Grad":"2"},"color":"rgb(192,192,192)","size":17.5},{"label":"Benghazi","x":-313.8926696777344,"y":-189.3642578125,"id":"80","attributes":{"Modularity Class":"4","Component ID":"0","Grad":"2"},"color":"rgb(95,165,253)","size":17.5},{"label":"PrimaryDay","x":712.2442016601562,"y":-296.4336242675781,"id":"62","attributes":{"Modularity Class":"41","Component ID":"0","Grad":"4"},"color":"rgb(192,192,192)","size":17.5},{"label":"iVoted","x":594.5142822265625,"y":-591.8096313476562,"id":"71","attributes":{"Modularity Class":"41","Component ID":"0","Grad":"1"},"color":"rgb(192,192,192)","size":17.5},{"label":"IAPolitics","x":986.0313720703125,"y":353.7741394042969,"id":"192","attributes":{"Modularity Class":"42","Component ID":"0","Grad":"4"},"color":"rgb(241,8,123)","size":17.5},{"label":"FoxNews","x":735.1604614257812,"y":698.9041748046875,"id":"26","attributes":{"Modularity Class":"19","Component ID":"0","Grad":"4"},"color":"rgb(192,192,192)","size":17.5},{"label":"MaryBrigidMcManamon","x":-924.1708984375,"y":699.3258666992188,"id":"88","attributes":{"Modularity Class":"9","Component ID":"9","Grad":"4"},"color":"rgb(192,192,192)","size":17.5},{"label":"DavidCameron","x":-871.74365234375,"y":-100.73432159423828,"id":"37","attributes":{"Modularity Class":"7","Component ID":"14","Grad":"1"},"color":"rgb(192,192,192)","size":17.5},{"label":"smallbiz","x":-207.8775177001953,"y":-347.9529724121094,"id":"78","attributes":{"Modularity Class":"27","Component ID":"21","Grad":"1"},"color":"rgb(192,192,192)","size":17.5},{"label":"Trump2016","x":461.98565673828125,"y":233.6415252685547,"id":"203","attributes":{"Modularity Class":"42","Component ID":"0","Grad":"52"},"color":"rgb(241,8,123)","size":17.5},{"label":"TrumpPence2016","x":9.828197479248047,"y":855.5744018554688,"id":"114","attributes":{"Modularity Class":"0","Component ID":"0","Grad":"2"},"color":"rgb(192,192,192)","size":17.5},{"label":"Elkhart","x":991.2590942382812,"y":-210.4178466796875,"id":"122","attributes":{"Modularity Class":"41","Component ID":"0","Grad":"2"},"color":"rgb(192,192,192)","size":17.5},{"label":"LESM","x":61.753658294677734,"y":201.92864990234375,"id":"22","attributes":{"Modularity Class":"4","Component ID":"0","Grad":"3"},"color":"rgb(95,165,253)","size":17.5},{"label":"veterans","x":-179.05528259277344,"y":-622.5050048828125,"id":"163","attributes":{"Modularity Class":"25","Component ID":"25","Grad":"1"},"color":"rgb(192,192,192)","size":17.5},{"label":"2A","x":163.2664337158203,"y":895.1552734375,"id":"1","attributes":{"Modularity Class":"0","Component ID":"0","Grad":"6"},"color":"rgb(192,192,192)","size":17.5},{"label":"MSM","x":-598.5001220703125,"y":-243.02757263183594,"id":"217","attributes":{"Modularity Class":"44","Component ID":"33","Grad":"1"},"color":"rgb(192,192,192)","size":17.5},{"label":"WH","x":-723.4202270507812,"y":-110.36043548583984,"id":"179","attributes":{"Modularity Class":"7","Component ID":"14","Grad":"1"},"color":"rgb(192,192,192)","size":17.5},{"label":"NHPrimary","x":1005.5867919921875,"y":581.1525268554688,"id":"17","attributes":{"Modularity Class":"32","Component ID":"0","Grad":"2"},"color":"rgb(192,192,192)","size":17.5},{"label":"Srebrenica","x":33.83541488647461,"y":-484.891845703125,"id":"77","attributes":{"Modularity Class":"20","Component ID":"20","Grad":"1"},"color":"rgb(192,192,192)","size":17.5},{"label":"ArizonaPrimary","x":872.6773681640625,"y":273.49334716796875,"id":"230","attributes":{"Modularity Class":"33","Component ID":"0","Grad":"7"},"color":"rgb(192,192,192)","size":17.5},{"label":"EauClaire","x":455.489990234375,"y":647.1322631835938,"id":"43","attributes":{"Modularity Class":"41","Component ID":"0","Grad":"5"},"color":"rgb(192,192,192)","size":17.5},{"label":"StrongerTogether","x":-779.8840942382812,"y":420.1494445800781,"id":"123","attributes":{"Modularity Class":"26","Component ID":"26","Grad":"1"},"color":"rgb(192,192,192)","size":17.5},{"label":"With_Cruz_you_lose","x":498.8189392089844,"y":-464.5232238769531,"id":"92","attributes":{"Modularity Class":"42","Component ID":"0","Grad":"2"},"color":"rgb(241,8,123)","size":17.5},{"label":"Cruz","x":-856.0092163085938,"y":547.6345825195312,"id":"184","attributes":{"Modularity Class":"9","Component ID":"9","Grad":"1"},"color":"rgb(192,192,192)","size":17.5}],"edges":[{"source":"23","target":"210","id":"67","attributes":{},"color":"rgb(241,8,123)","size":1.0},{"source":"75","target":"180","id":"172","attributes":{},"color":"rgb(192,192,192)","size":1.0},{"source":"177","target":"203","id":"311","attributes":{},"color":"rgb(216,100,157)","size":1.0},{"source":"73","target":"219","id":"167","attributes":{},"color":"rgb(192,192,192)","size":1.0},{"source":"104","target":"171","id":"213","attributes":{},"color":"rgb(192,192,192)","size":1.0},{"source":"162","target":"210","id":"301","attributes":{},"color":"rgb(168,86,188)","size":1.0},{"source":"26","target":"203","id":"74","attributes":{},"color":"rgb(216,100,157)","size":2.0},{"source":"14","target":"230","id":"39","attributes":{},"color":"rgb(192,192,192)","size":2.0},{"source":"22","target":"212","id":"64","attributes":{},"color":"rgb(95,165,253)","size":2.0},{"source":"15","target":"210","id":"42","attributes":{},"color":"rgb(241,8,123)","size":1.0},{"source":"133","target":"229","id":"270","attributes":{},"color":"rgb(192,192,192)","size":1.0},{"source":"10","target":"50","id":"27","attributes":{},"color":"rgb(192,192,192)","size":1.0},{"source":"149","target":"165","id":"289","attributes":{},"color":"rgb(192,192,192)","size":1.0},{"source":"137","target":"212","id":"281","attributes":{},"color":"rgb(95,165,253)","size":5.0},{"source":"43","target":"223","id":"121","attributes":{},"color":"rgb(192,192,192)","size":1.0},{"source":"95","target":"210","id":"196","attributes":{},"color":"rgb(241,8,123)","size":1.0},{"source":"3","target":"215","id":"14","attributes":{},"color":"rgb(192,192,192)","size":1.0},{"source":"14","target":"113","id":"41","attributes":{},"color":"rgb(192,192,192)","size":1.0},{"source":"197","target":"203","id":"334","attributes":{},"color":"rgb(241,8,123)","size":1.0},{"source":"200","target":"210","id":"338","attributes":{},"color":"rgb(216,100,157)","size":1.0},{"source":"14","target":"208","id":"40","attributes":{},"color":"rgb(216,100,157)","size":2.0},{"source":"127","target":"205","id":"260","attributes":{},"color":"rgb(95,165,253)","size":1.0},{"source":"198","target":"213","id":"335","attributes":{},"color":"rgb(192,192,192)","size":1.0},{"source":"203","target":"207","id":"343","attributes":{},"color":"rgb(216,100,157)","size":1.0},{"source":"55","target":"161","id":"139","attributes":{},"color":"rgb(192,192,192)","size":1.0},{"source":"30","target":"183","id":"89","attributes":{},"color":"rgb(95,165,253)","size":2.0},{"source":"134","target":"188","id":"273","attributes":{},"color":"rgb(192,192,192)","size":1.0},{"source":"65","target":"81","id":"158","attributes":{},"color":"rgb(192,192,192)","size":1.0},{"source":"145","target":"211","id":"288","attributes":{},"color":"rgb(192,192,192)","size":1.0},{"source":"42","target":"126","id":"120","attributes":{},"color":"rgb(95,165,253)","size":1.0},{"source":"51","target":"204","id":"133","attributes":{},"color":"rgb(192,192,192)","size":1.0},{"source":"110","target":"198","id":"221","attributes":{},"color":"rgb(192,192,192)","size":1.0},{"source":"127","target":"212","id":"263","attributes":{},"color":"rgb(95,165,253)","size":3.0},{"source":"190","target":"198","id":"329","attributes":{},"color":"rgb(192,192,192)","size":1.0},{"source":"1","target":"203","id":"6","attributes":{},"color":"rgb(216,100,157)","size":1.0},{"source":"28","target":"203","id":"76","attributes":{},"color":"rgb(241,8,123)","size":1.0},{"source":"141","target":"210","id":"283","attributes":{},"color":"rgb(168,86,188)","size":1.0},{"source":"158","target":"210","id":"300","attributes":{},"color":"rgb(241,8,123)","size":1.0},{"source":"141","target":"183","id":"285","attributes":{},"color":"rgb(95,165,253)","size":2.0},{"source":"68","target":"174","id":"161","attributes":{},"color":"rgb(192,192,192)","size":1.0},{"source":"113","target":"230","id":"231","attributes":{},"color":"rgb(192,192,192)","size":1.0},{"source":"189","target":"210","id":"327","attributes":{},"color":"rgb(216,100,157)","size":2.0},{"source":"12","target":"143","id":"31","attributes":{},"color":"rgb(192,192,192)","size":1.0},{"source":"30","target":"180","id":"85","attributes":{},"color":"rgb(143,178,222)","size":2.0},{"source":"137","target":"180","id":"280","attributes":{},"color":"rgb(143,178,222)","size":1.0},{"source":"120","target":"199","id":"245","attributes":{},"color":"rgb(192,192,192)","size":1.0},{"source":"82","target":"195","id":"184","attributes":{},"color":"rgb(192,192,192)","size":1.0},{"source":"41","target":"88","id":"117","attributes":{},"color":"rgb(192,192,192)","size":1.0},{"source":"74","target":"203","id":"169","attributes":{},"color":"rgb(241,8,123)","size":1.0},{"source":"107","target":"203","id":"217","attributes":{},"color":"rgb(241,8,123)","size":1.0},{"source":"43","target":"180","id":"125","attributes":{},"color":"rgb(192,192,192)","size":1.0},{"source":"111","target":"192","id":"223","attributes":{},"color":"rgb(216,100,157)","size":1.0},{"source":"40","target":"208","id":"114","attributes":{},"color":"rgb(216,100,157)","size":1.0},{"source":"203","target":"212","id":"345","attributes":{},"color":"rgb(168,86,188)","size":4.0},{"source":"54","target":"185","id":"137","attributes":{},"color":"rgb(192,192,192)","size":1.0},{"source":"121","target":"208","id":"253","attributes":{},"color":"rgb(216,100,157)","size":1.0},{"source":"0","target":"111","id":"2","attributes":{},"color":"rgb(192,192,192)","size":6.0},{"source":"98","target":"157","id":"207","attributes":{},"color":"rgb(192,192,192)","size":1.0},{"source":"111","target":"210","id":"222","attributes":{},"color":"rgb(216,100,157)","size":3.0},{"source":"120","target":"132","id":"247","attributes":{},"color":"rgb(192,192,192)","size":1.0},{"source":"80","target":"127","id":"180","attributes":{},"color":"rgb(95,165,253)","size":1.0},{"source":"13","target":"70","id":"34","attributes":{},"color":"rgb(192,192,192)","size":1.0},{"source":"180","target":"201","id":"314","attributes":{},"color":"rgb(192,192,192)","size":1.0},{"source":"57","target":"216","id":"142","attributes":{},"color":"rgb(192,192,192)","size":1.0},{"source":"97","target":"186","id":"204","attributes":{},"color":"rgb(241,8,123)","size":3.0},{"source":"116","target":"151","id":"236","attributes":{},"color":"rgb(192,192,192)","size":1.0},{"source":"185","target":"221","id":"325","attributes":{},"color":"rgb(192,192,192)","size":1.0},{"source":"30","target":"137","id":"86","attributes":{},"color":"rgb(95,165,253)","size":12.0},{"source":"30","target":"42","id":"84","attributes":{},"color":"rgb(95,165,253)","size":2.0},{"source":"8","target":"31","id":"23","attributes":{},"color":"rgb(95,165,253)","size":1.0},{"source":"26","target":"73","id":"72","attributes":{},"color":"rgb(192,192,192)","size":1.0},{"source":"137","target":"208","id":"278","attributes":{},"color":"rgb(168,86,188)","size":1.0},{"source":"111","target":"139","id":"225","attributes":{},"color":"rgb(192,192,192)","size":1.0},{"source":"154","target":"159","id":"298","attributes":{},"color":"rgb(192,192,192)","size":1.0},{"source":"57","target":"174","id":"145","attributes":{},"color":"rgb(192,192,192)","size":1.0},{"source":"14","target":"203","id":"38","attributes":{},"color":"rgb(216,100,157)","size":2.0},{"source":"3","target":"81","id":"15","attributes":{},"color":"rgb(192,192,192)","size":1.0},{"source":"132","target":"206","id":"268","attributes":{},"color":"rgb(192,192,192)","size":1.0},{"source":"24","target":"58","id":"69","attributes":{},"color":"rgb(192,192,192)","size":1.0},{"source":"205","target":"226","id":"349","attributes":{},"color":"rgb(95,165,253)","size":1.0},{"source":"36","target":"222","id":"106","attributes":{},"color":"rgb(192,192,192)","size":1.0},{"source":"19","target":"208","id":"51","attributes":{},"color":"rgb(241,8,123)","size":1.0},{"source":"11","target":"44","id":"30","attributes":{},"color":"rgb(192,192,192)","size":1.0},{"source":"59","target":"214","id":"147","attributes":{},"color":"rgb(95,165,253)","size":1.0},{"source":"202","target":"203","id":"341","attributes":{},"color":"rgb(241,8,123)","size":1.0},{"source":"30","target":"63","id":"81","attributes":{},"color":"rgb(95,165,253)","size":1.0},{"source":"122","target":"200","id":"255","attributes":{},"color":"rgb(192,192,192)","size":1.0},{"source":"50","target":"57","id":"131","attributes":{},"color":"rgb(192,192,192)","size":1.0},{"source":"52","target":"203","id":"135","attributes":{},"color":"rgb(241,8,123)","size":1.0},{"source":"113","target":"210","id":"232","attributes":{},"color":"rgb(216,100,157)","size":1.0},{"source":"72","target":"203","id":"166","attributes":{},"color":"rgb(241,8,123)","size":3.0},{"source":"69","target":"203","id":"163","attributes":{},"color":"rgb(241,8,123)","size":1.0},{"source":"153","target":"230","id":"297","attributes":{},"color":"rgb(192,192,192)","size":1.0},{"source":"36","target":"103","id":"105","attributes":{},"color":"rgb(192,192,192)","size":1.0},{"source":"208","target":"210","id":"351","attributes":{},"color":"rgb(241,8,123)","size":18.0},{"source":"30","target":"141","id":"80","attributes":{},"color":"rgb(95,165,253)","size":4.0},{"source":"137","target":"203","id":"282","attributes":{},"color":"rgb(168,86,188)","size":2.0},{"source":"40","target":"153","id":"111","attributes":{},"color":"rgb(192,192,192)","size":1.0},{"source":"33","target":"58","id":"100","attributes":{},"color":"rgb(192,192,192)","size":1.0},{"source":"115","target":"137","id":"235","attributes":{},"color":"rgb(95,165,253)","size":1.0},{"source":"114","target":"141","id":"234","attributes":{},"color":"rgb(143,178,222)","size":1.0},{"source":"16","target":"100","id":"45","attributes":{},"color":"rgb(241,8,123)","size":1.0},{"source":"127","target":"164","id":"259","attributes":{},"color":"rgb(95,165,253)","size":1.0},{"source":"116","target":"145","id":"237","attributes":{},"color":"rgb(192,192,192)","size":1.0},{"source":"203","target":"225","id":"347","attributes":{},"color":"rgb(216,100,157)","size":1.0},{"source":"207","target":"223","id":"350","attributes":{},"color":"rgb(192,192,192)","size":1.0},{"source":"8","target":"137","id":"22","attributes":{},"color":"rgb(95,165,253)","size":1.0},{"source":"14","target":"210","id":"35","attributes":{},"color":"rgb(216,100,157)","size":2.0},{"source":"4","target":"203","id":"17","attributes":{},"color":"rgb(241,8,123)","size":1.0},{"source":"40","target":"230","id":"113","attributes":{},"color":"rgb(192,192,192)","size":1.0},{"source":"98","target":"123","id":"206","attributes":{},"color":"rgb(192,192,192)","size":1.0},{"source":"150","target":"165","id":"293","attributes":{},"color":"rgb(192,192,192)","size":1.0},{"source":"135","target":"221","id":"275","attributes":{},"color":"rgb(192,192,192)","size":1.0},{"source":"97","target":"189","id":"199","attributes":{},"color":"rgb(216,100,157)","size":1.0},{"source":"112","target":"210","id":"227","attributes":{},"color":"rgb(241,8,123)","size":1.0},{"source":"111","target":"203","id":"224","attributes":{},"color":"rgb(216,100,157)","size":9.0},{"source":"54","target":"146","id":"138","attributes":{},"color":"rgb(192,192,192)","size":1.0},{"source":"68","target":"216","id":"162","attributes":{},"color":"rgb(192,192,192)","size":1.0},{"source":"109","target":"148","id":"218","attributes":{},"color":"rgb(192,192,192)","size":1.0},{"source":"124","target":"144","id":"257","attributes":{},"color":"rgb(95,165,253)","size":1.0},{"source":"34","target":"204","id":"101","attributes":{},"color":"rgb(192,192,192)","size":1.0},{"source":"26","target":"210","id":"71","attributes":{},"color":"rgb(216,100,157)","size":1.0},{"source":"32","target":"132","id":"98","attributes":{},"color":"rgb(192,192,192)","size":1.0},{"source":"113","target":"153","id":"229","attributes":{},"color":"rgb(192,192,192)","size":1.0},{"source":"30","target":"210","id":"83","attributes":{},"color":"rgb(168,86,188)","size":2.0},{"source":"110","target":"190","id":"220","attributes":{},"color":"rgb(192,192,192)","size":1.0},{"source":"29","target":"41","id":"78","attributes":{},"color":"rgb(192,192,192)","size":1.0},{"source":"31","target":"124","id":"94","attributes":{},"color":"rgb(95,165,253)","size":1.0},{"source":"103","target":"222","id":"212","attributes":{},"color":"rgb(192,192,192)","size":1.0},{"source":"176","target":"212","id":"310","attributes":{},"color":"rgb(95,165,253)","size":1.0},{"source":"92","target":"169","id":"193","attributes":{},"color":"rgb(241,8,123)","size":1.0},{"source":"20","target":"203","id":"60","attributes":{},"color":"rgb(216,100,157)","size":2.0},{"source":"43","target":"203","id":"122","attributes":{},"color":"rgb(216,100,157)","size":1.0},{"source":"79","target":"208","id":"178","attributes":{},"color":"rgb(241,8,123)","size":6.0},{"source":"20","target":"62","id":"59","attributes":{},"color":"rgb(192,192,192)","size":1.0},{"source":"113","target":"203","id":"230","attributes":{},"color":"rgb(216,100,157)","size":1.0},{"source":"114","target":"133","id":"233","attributes":{},"color":"rgb(192,192,192)","size":1.0},{"source":"171","target":"177","id":"306","attributes":{},"color":"rgb(192,192,192)","size":1.0},{"source":"86","target":"177","id":"188","attributes":{},"color":"rgb(192,192,192)","size":1.0},{"source":"200","target":"203","id":"339","attributes":{},"color":"rgb(216,100,157)","size":2.0},{"source":"19","target":"55","id":"53","attributes":{},"color":"rgb(216,100,157)","size":1.0},{"source":"99","target":"203","id":"208","attributes":{},"color":"rgb(241,8,123)","size":1.0},{"source":"178","target":"197","id":"312","attributes":{},"color":"rgb(241,8,123)","size":1.0},{"source":"31","target":"128","id":"93","attributes":{},"color":"rgb(95,165,253)","size":1.0},{"source":"134","target":"189","id":"272","attributes":{},"color":"rgb(192,192,192)","size":1.0},{"source":"167","target":"181","id":"303","attributes":{},"color":"rgb(192,192,192)","size":1.0},{"source":"30","target":"203","id":"82","attributes":{},"color":"rgb(168,86,188)","size":12.0},{"source":"41","target":"89","id":"116","attributes":{},"color":"rgb(192,192,192)","size":1.0},{"source":"133","target":"212","id":"269","attributes":{},"color":"rgb(143,178,222)","size":1.0},{"source":"26","target":"219","id":"73","attributes":{},"color":"rgb(192,192,192)","size":1.0},{"source":"121","target":"203","id":"252","attributes":{},"color":"rgb(216,100,157)","size":10.0},{"source":"180","target":"207","id":"316","attributes":{},"color":"rgb(192,192,192)","size":1.0},{"source":"208","target":"230","id":"352","attributes":{},"color":"rgb(216,100,157)","size":1.0},{"source":"59","target":"212","id":"146","attributes":{},"color":"rgb(95,165,253)","size":1.0},{"source":"19","target":"149","id":"52","attributes":{},"color":"rgb(216,100,157)","size":1.0},{"source":"31","target":"42","id":"92","attributes":{},"color":"rgb(95,165,253)","size":1.0},{"source":"47","target":"127","id":"127","attributes":{},"color":"rgb(95,165,253)","size":1.0},{"source":"180","target":"210","id":"318","attributes":{},"color":"rgb(216,100,157)","size":8.0},{"source":"94","target":"108","id":"195","attributes":{},"color":"rgb(192,192,192)","size":1.0},{"source":"22","target":"203","id":"66","attributes":{},"color":"rgb(168,86,188)","size":1.0},{"source":"210","target":"230","id":"353","attributes":{},"color":"rgb(216,100,157)","size":1.0},{"source":"31","target":"212","id":"95","attributes":{},"color":"rgb(95,165,253)","size":5.0},{"source":"10","target":"216","id":"28","attributes":{},"color":"rgb(192,192,192)","size":1.0},{"source":"180","target":"225","id":"321","attributes":{},"color":"rgb(192,192,192)","size":1.0},{"source":"182","target":"216","id":"323","attributes":{},"color":"rgb(192,192,192)","size":1.0},{"source":"18","target":"203","id":"50","attributes":{},"color":"rgb(241,8,123)","size":1.0},{"source":"30","target":"127","id":"79","attributes":{},"color":"rgb(95,165,253)","size":1.0},{"source":"0","target":"17","id":"3","attributes":{},"color":"rgb(192,192,192)","size":2.0},{"source":"76","target":"133","id":"173","attributes":{},"color":"rgb(192,192,192)","size":1.0},{"source":"166","target":"221","id":"302","attributes":{},"color":"rgb(192,192,192)","size":1.0},{"source":"121","target":"180","id":"250","attributes":{},"color":"rgb(192,192,192)","size":1.0},{"source":"96","target":"163","id":"198","attributes":{},"color":"rgb(192,192,192)","size":1.0},{"source":"97","target":"208","id":"205","attributes":{},"color":"rgb(241,8,123)","size":2.0},{"source":"38","target":"187","id":"108","attributes":{},"color":"rgb(192,192,192)","size":1.0},{"source":"141","target":"162","id":"284","attributes":{},"color":"rgb(95,165,253)","size":1.0},{"source":"8","target":"203","id":"24","attributes":{},"color":"rgb(168,86,188)","size":1.0},{"source":"30","target":"212","id":"88","attributes":{},"color":"rgb(95,165,253)","size":5.0},{"source":"15","target":"72","id":"43","attributes":{},"color":"rgb(241,8,123)","size":2.0},{"source":"34","target":"51","id":"102","attributes":{},"color":"rgb(192,192,192)","size":1.0},{"source":"39","target":"203","id":"109","attributes":{},"color":"rgb(241,8,123)","size":2.0},{"source":"22","target":"210","id":"65","attributes":{},"color":"rgb(168,86,188)","size":1.0},{"source":"192","target":"208","id":"330","attributes":{},"color":"rgb(241,8,123)","size":1.0},{"source":"24","target":"33","id":"68","attributes":{},"color":"rgb(192,192,192)","size":1.0},{"source":"50","target":"174","id":"130","attributes":{},"color":"rgb(192,192,192)","size":1.0},{"source":"168","target":"203","id":"304","attributes":{},"color":"rgb(241,8,123)","size":1.0},{"source":"5","target":"91","id":"18","attributes":{},"color":"rgb(192,192,192)","size":1.0},{"source":"60","target":"138","id":"149","attributes":{},"color":"rgb(192,192,192)","size":1.0},{"source":"121","target":"210","id":"248","attributes":{},"color":"rgb(216,100,157)","size":1.0},{"source":"93","target":"155","id":"194","attributes":{},"color":"rgb(192,192,192)","size":1.0},{"source":"42","target":"137","id":"118","attributes":{},"color":"rgb(95,165,253)","size":1.0},{"source":"70","target":"228","id":"164","attributes":{},"color":"rgb(192,192,192)","size":1.0},{"source":"117","target":"211","id":"242","attributes":{},"color":"rgb(192,192,192)","size":1.0},{"source":"132","target":"208","id":"267","attributes":{},"color":"rgb(216,100,157)","size":1.0},{"source":"101","target":"212","id":"210","attributes":{},"color":"rgb(95,165,253)","size":1.0},{"source":"29","target":"88","id":"77","attributes":{},"color":"rgb(192,192,192)","size":1.0},{"source":"105","target":"215","id":"214","attributes":{},"color":"rgb(192,192,192)","size":1.0},{"source":"75","target":"212","id":"170","attributes":{},"color":"rgb(143,178,222)","size":1.0},{"source":"97","target":"111","id":"201","attributes":{},"color":"rgb(216,100,157)","size":4.0},{"source":"13","target":"228","id":"33","attributes":{},"color":"rgb(192,192,192)","size":1.0},{"source":"194","target":"231","id":"333","attributes":{},"color":"rgb(192,192,192)","size":1.0},{"source":"203","target":"230","id":"348","attributes":{},"color":"rgb(216,100,157)","size":1.0},{"source":"85","target":"218","id":"187","attributes":{},"color":"rgb(192,192,192)","size":1.0},{"source":"127","target":"226","id":"261","attributes":{},"color":"rgb(95,165,253)","size":1.0},{"source":"62","target":"200","id":"152","attributes":{},"color":"rgb(192,192,192)","size":1.0},{"source":"107","target":"208","id":"216","attributes":{},"color":"rgb(241,8,123)","size":1.0},{"source":"79","target":"203","id":"179","attributes":{},"color":"rgb(241,8,123)","size":3.0},{"source":"40","target":"113","id":"115","attributes":{},"color":"rgb(192,192,192)","size":2.0},{"source":"57","target":"83","id":"143","attributes":{},"color":"rgb(192,192,192)","size":1.0},{"source":"37","target":"179","id":"107","attributes":{},"color":"rgb(192,192,192)","size":1.0},{"source":"10","target":"174","id":"26","attributes":{},"color":"rgb(192,192,192)","size":1.0},{"source":"97","target":"203","id":"203","attributes":{},"color":"rgb(241,8,123)","size":8.0},{"source":"116","target":"117","id":"239","attributes":{},"color":"rgb(192,192,192)","size":1.0},{"source":"188","target":"189","id":"326","attributes":{},"color":"rgb(192,192,192)","size":1.0},{"source":"81","target":"105","id":"182","attributes":{},"color":"rgb(192,192,192)","size":1.0},{"source":"121","target":"223","id":"249","attributes":{},"color":"rgb(192,192,192)","size":1.0},{"source":"3","target":"65","id":"16","attributes":{},"color":"rgb(192,192,192)","size":1.0},{"source":"16","target":"203","id":"48","attributes":{},"color":"rgb(241,8,123)","size":12.0},{"source":"122","target":"210","id":"256","attributes":{},"color":"rgb(216,100,157)","size":1.0},{"source":"137","target":"210","id":"277","attributes":{},"color":"rgb(168,86,188)","size":6.0},{"source":"137","target":"224","id":"279","attributes":{},"color":"rgb(95,165,253)","size":2.0},{"source":"77","target":"125","id":"175","attributes":{},"color":"rgb(192,192,192)","size":1.0},{"source":"74","target":"173","id":"168","attributes":{},"color":"rgb(241,8,123)","size":1.0},{"source":"76","target":"147","id":"174","attributes":{},"color":"rgb(192,192,192)","size":1.0},{"source":"95","target":"203","id":"197","attributes":{},"color":"rgb(241,8,123)","size":1.0},{"source":"31","target":"144","id":"91","attributes":{},"color":"rgb(95,165,253)","size":1.0},{"source":"72","target":"210","id":"165","attributes":{},"color":"rgb(241,8,123)","size":3.0},{"source":"50","target":"216","id":"132","attributes":{},"color":"rgb(192,192,192)","size":1.0},{"source":"169","target":"210","id":"305","attributes":{},"color":"rgb(241,8,123)","size":2.0},{"source":"6","target":"159","id":"19","attributes":{},"color":"rgb(192,192,192)","size":1.0},{"source":"62","target":"71","id":"151","attributes":{},"color":"rgb(192,192,192)","size":1.0},{"source":"116","target":"211","id":"238","attributes":{},"color":"rgb(192,192,192)","size":1.0},{"source":"92","target":"210","id":"192","attributes":{},"color":"rgb(241,8,123)","size":1.0},{"source":"193","target":"217","id":"332","attributes":{},"color":"rgb(192,192,192)","size":1.0},{"source":"203","target":"208","id":"342","attributes":{},"color":"rgb(241,8,123)","size":14.0},{"source":"203","target":"223","id":"346","attributes":{},"color":"rgb(216,100,157)","size":1.0},{"source":"119","target":"138","id":"244","attributes":{},"color":"rgb(192,192,192)","size":1.0},{"source":"111","target":"208","id":"226","attributes":{},"color":"rgb(216,100,157)","size":2.0},{"source":"133","target":"147","id":"271","attributes":{},"color":"rgb(192,192,192)","size":1.0},{"source":"45","target":"227","id":"126","attributes":{},"color":"rgb(192,192,192)","size":1.0},{"source":"75","target":"203","id":"171","attributes":{},"color":"rgb(216,100,157)","size":1.0},{"source":"27","target":"208","id":"75","attributes":{},"color":"rgb(241,8,123)","size":1.0},{"source":"56","target":"221","id":"141","attributes":{},"color":"rgb(192,192,192)","size":1.0},{"source":"185","target":"196","id":"324","attributes":{},"color":"rgb(192,192,192)","size":1.0},{"source":"121","target":"212","id":"251","attributes":{},"color":"rgb(143,178,222)","size":1.0},{"source":"1","target":"133","id":"7","attributes":{},"color":"rgb(192,192,192)","size":2.0},{"source":"1","target":"229","id":"5","attributes":{},"color":"rgb(192,192,192)","size":1.0},{"source":"190","target":"213","id":"328","attributes":{},"color":"rgb(192,192,192)","size":1.0},{"source":"7","target":"30","id":"21","attributes":{},"color":"rgb(95,165,253)","size":1.0},{"source":"175","target":"210","id":"309","attributes":{},"color":"rgb(241,8,123)","size":1.0},{"source":"66","target":"203","id":"160","attributes":{},"color":"rgb(216,100,157)","size":2.0},{"source":"20","target":"90","id":"56","attributes":{},"color":"rgb(192,192,192)","size":1.0},{"source":"145","target":"151","id":"287","attributes":{},"color":"rgb(192,192,192)","size":1.0},{"source":"32","target":"206","id":"99","attributes":{},"color":"rgb(192,192,192)","size":1.0},{"source":"55","target":"64","id":"140","attributes":{},"color":"rgb(192,192,192)","size":1.0},{"source":"178","target":"203","id":"313","attributes":{},"color":"rgb(241,8,123)","size":1.0},{"source":"48","target":"221","id":"128","attributes":{},"color":"rgb(192,192,192)","size":1.0},{"source":"20","target":"200","id":"57","attributes":{},"color":"rgb(192,192,192)","size":1.0},{"source":"43","target":"207","id":"124","attributes":{},"color":"rgb(192,192,192)","size":1.0},{"source":"12","target":"84","id":"32","attributes":{},"color":"rgb(192,192,192)","size":1.0},{"source":"40","target":"203","id":"112","attributes":{},"color":"rgb(216,100,157)","size":1.0},{"source":"9","target":"140","id":"25","attributes":{},"color":"rgb(192,192,192)","size":1.0},{"source":"79","target":"210","id":"177","attributes":{},"color":"rgb(241,8,123)","size":1.0},{"source":"120","target":"206","id":"246","attributes":{},"color":"rgb(192,192,192)","size":1.0},{"source":"151","target":"211","id":"294","attributes":{},"color":"rgb(192,192,192)","size":1.0},{"source":"2","target":"87","id":"11","attributes":{},"color":"rgb(192,192,192)","size":4.0},{"source":"35","target":"218","id":"103","attributes":{},"color":"rgb(192,192,192)","size":1.0},{"source":"64","target":"161","id":"155","attributes":{},"color":"rgb(192,192,192)","size":1.0},{"source":"57","target":"131","id":"144","attributes":{},"color":"rgb(192,192,192)","size":1.0},{"source":"106","target":"130","id":"215","attributes":{},"color":"rgb(192,192,192)","size":1.0},{"source":"2","target":"203","id":"12","attributes":{},"color":"rgb(216,100,157)","size":2.0},{"source":"3","target":"105","id":"13","attributes":{},"color":"rgb(192,192,192)","size":1.0},{"source":"180","target":"191","id":"320","attributes":{},"color":"rgb(192,192,192)","size":1.0},{"source":"16","target":"208","id":"47","attributes":{},"color":"rgb(241,8,123)","size":5.0},{"source":"121","target":"207","id":"254","attributes":{},"color":"rgb(192,192,192)","size":1.0},{"source":"192","target":"203","id":"331","attributes":{},"color":"rgb(241,8,123)","size":1.0},{"source":"1","target":"220","id":"8","attributes":{},"color":"rgb(192,192,192)","size":1.0},{"source":"14","target":"40","id":"37","attributes":{},"color":"rgb(192,192,192)","size":1.0},{"source":"32","target":"120","id":"97","attributes":{},"color":"rgb(192,192,192)","size":1.0},{"source":"117","target":"151","id":"240","attributes":{},"color":"rgb(192,192,192)","size":1.0},{"source":"124","target":"128","id":"258","attributes":{},"color":"rgb(95,165,253)","size":1.0},{"source":"173","target":"203","id":"307","attributes":{},"color":"rgb(241,8,123)","size":1.0},{"source":"10","target":"57","id":"29","attributes":{},"color":"rgb(192,192,192)","size":1.0},{"source":"117","target":"145","id":"241","attributes":{},"color":"rgb(192,192,192)","size":1.0},{"source":"30","target":"31","id":"90","attributes":{},"color":"rgb(95,165,253)","size":1.0},{"source":"65","target":"105","id":"156","attributes":{},"color":"rgb(192,192,192)","size":1.0},{"source":"0","target":"210","id":"1","attributes":{},"color":"rgb(216,100,157)","size":1.0},{"source":"97","target":"192","id":"202","attributes":{},"color":"rgb(241,8,123)","size":1.0},{"source":"199","target":"206","id":"337","attributes":{},"color":"rgb(192,192,192)","size":1.0},{"source":"53","target":"212","id":"136","attributes":{},"color":"rgb(95,165,253)","size":1.0},{"source":"40","target":"210","id":"110","attributes":{},"color":"rgb(216,100,157)","size":1.0},{"source":"203","target":"210","id":"344","attributes":{},"color":"rgb(241,8,123)","size":103.0},{"source":"90","target":"203","id":"191","attributes":{},"color":"rgb(216,100,157)","size":1.0},{"source":"0","target":"139","id":"0","attributes":{},"color":"rgb(192,192,192)","size":1.0},{"source":"20","target":"210","id":"58","attributes":{},"color":"rgb(216,100,157)","size":1.0},{"source":"153","target":"208","id":"296","attributes":{},"color":"rgb(216,100,157)","size":1.0},{"source":"81","target":"215","id":"183","attributes":{},"color":"rgb(192,192,192)","size":1.0},{"source":"110","target":"213","id":"219","attributes":{},"color":"rgb(192,192,192)","size":1.0},{"source":"1","target":"76","id":"4","attributes":{},"color":"rgb(192,192,192)","size":1.0},{"source":"1","target":"147","id":"9","attributes":{},"color":"rgb(192,192,192)","size":1.0},{"source":"6","target":"154","id":"20","attributes":{},"color":"rgb(192,192,192)","size":1.0},{"source":"100","target":"210","id":"209","attributes":{},"color":"rgb(241,8,123)","size":1.0},{"source":"97","target":"210","id":"200","attributes":{},"color":"rgb(241,8,123)","size":6.0},{"source":"17","target":"111","id":"49","attributes":{},"color":"rgb(192,192,192)","size":6.0},{"source":"118","target":"215","id":"243","attributes":{},"color":"rgb(192,192,192)","size":1.0},{"source":"32","target":"199","id":"96","attributes":{},"color":"rgb(192,192,192)","size":1.0},{"source":"84","target":"143","id":"186","attributes":{},"color":"rgb(192,192,192)","size":1.0},{"source":"90","target":"169","id":"190","attributes":{},"color":"rgb(216,100,157)","size":1.0},{"source":"136","target":"212","id":"276","attributes":{},"color":"rgb(95,165,253)","size":1.0},{"source":"180","target":"203","id":"315","attributes":{},"color":"rgb(216,100,157)","size":10.0},{"source":"15","target":"203","id":"44","attributes":{},"color":"rgb(241,8,123)","size":4.0},{"source":"156","target":"160","id":"299","attributes":{},"color":"rgb(192,192,192)","size":1.0},{"source":"35","target":"85","id":"104","attributes":{},"color":"rgb(192,192,192)","size":1.0},{"source":"43","target":"121","id":"123","attributes":{},"color":"rgb(192,192,192)","size":1.0},{"source":"65","target":"215","id":"157","attributes":{},"color":"rgb(192,192,192)","size":1.0},{"source":"16","target":"210","id":"46","attributes":{},"color":"rgb(241,8,123)","size":7.0},{"source":"21","target":"41","id":"63","attributes":{},"color":"rgb(192,192,192)","size":1.0},{"source":"78","target":"102","id":"176","attributes":{},"color":"rgb(192,192,192)","size":1.0},{"source":"62","target":"203","id":"153","attributes":{},"color":"rgb(216,100,157)","size":1.0},{"source":"19","target":"180","id":"55","attributes":{},"color":"rgb(216,100,157)","size":1.0},{"source":"180","target":"212","id":"322","attributes":{},"color":"rgb(143,178,222)","size":3.0},{"source":"2","target":"67","id":"10","attributes":{},"color":"rgb(192,192,192)","size":1.0},{"source":"66","target":"111","id":"159","attributes":{},"color":"rgb(192,192,192)","size":2.0},{"source":"149","target":"203","id":"292","attributes":{},"color":"rgb(216,100,157)","size":1.0},{"source":"101","target":"172","id":"211","attributes":{},"color":"rgb(95,165,253)","size":1.0},{"source":"49","target":"210","id":"129","attributes":{},"color":"rgb(241,8,123)","size":1.0},{"source":"132","target":"199","id":"266","attributes":{},"color":"rgb(192,192,192)","size":1.0},{"source":"129","target":"203","id":"265","attributes":{},"color":"rgb(241,8,123)","size":1.0},{"source":"14","target":"153","id":"36","attributes":{},"color":"rgb(192,192,192)","size":1.0},{"source":"19","target":"203","id":"54","attributes":{},"color":"rgb(241,8,123)","size":3.0},{"source":"199","target":"208","id":"336","attributes":{},"color":"rgb(216,100,157)","size":1.0},{"source":"149","target":"208","id":"290","attributes":{},"color":"rgb(216,100,157)","size":1.0},{"source":"61","target":"170","id":"150","attributes":{},"color":"rgb(192,192,192)","size":1.0},{"source":"88","target":"184","id":"189","attributes":{},"color":"rgb(192,192,192)","size":1.0},{"source":"63","target":"183","id":"154","attributes":{},"color":"rgb(95,165,253)","size":1.0},{"source":"83","target":"131","id":"185","attributes":{},"color":"rgb(192,192,192)","size":1.0},{"source":"113","target":"208","id":"228","attributes":{},"color":"rgb(216,100,157)","size":1.0},{"source":"180","target":"223","id":"319","attributes":{},"color":"rgb(192,192,192)","size":1.0},{"source":"174","target":"216","id":"308","attributes":{},"color":"rgb(192,192,192)","size":2.0},{"source":"21","target":"29","id":"61","attributes":{},"color":"rgb(192,192,192)","size":1.0},{"source":"201","target":"210","id":"340","attributes":{},"color":"rgb(216,100,157)","size":1.0},{"source":"135","target":"185","id":"274","attributes":{},"color":"rgb(192,192,192)","size":1.0},{"source":"152","target":"208","id":"295","attributes":{},"color":"rgb(241,8,123)","size":1.0},{"source":"42","target":"212","id":"119","attributes":{},"color":"rgb(95,165,253)","size":1.0},{"source":"30","target":"46","id":"87","attributes":{},"color":"rgb(95,165,253)","size":1.0},{"source":"25","target":"121","id":"70","attributes":{},"color":"rgb(192,192,192)","size":1.0},{"source":"52","target":"210","id":"134","attributes":{},"color":"rgb(241,8,123)","size":1.0},{"source":"60","target":"119","id":"148","attributes":{},"color":"rgb(192,192,192)","size":1.0},{"source":"80","target":"164","id":"181","attributes":{},"color":"rgb(95,165,253)","size":1.0},{"source":"127","target":"209","id":"262","attributes":{},"color":"rgb(95,165,253)","size":1.0},{"source":"128","target":"144","id":"264","attributes":{},"color":"rgb(95,165,253)","size":1.0},{"source":"21","target":"88","id":"62","attributes":{},"color":"rgb(192,192,192)","size":1.0},{"source":"142","target":"210","id":"286","attributes":{},"color":"rgb(241,8,123)","size":1.0},{"source":"149","target":"150","id":"291","attributes":{},"color":"rgb(192,192,192)","size":1.0},{"source":"180","target":"189","id":"317","attributes":{},"color":"rgb(192,192,192)","size":1.0}]}